Metadata-Version: 1.0
Name: pydatamake
Version: 0.11
Summary: pydatamake
Home-page: UNKNOWN
Author: lijun
Author-email: asdfzxcvqwer123a@126.com
License: MIT
Platform: UNKNOWN
